CubeRaspberryLib3/__init__.py
CubeRaspberryLib3/module.py
cuberaspberrylib3-0.1.15.dist-info/licenses/LICENSE
cuberaspberrylib3-0.1.15.dist-info/METADATA
cuberaspberrylib3-0.1.15.dist-info/WHEEL
cuberaspberrylib3-0.1.15.dist-info/top_level.txt
cuberaspberrylib3-0.1.15.dist-info/RECORD
