Metadata-Version: 2.4
Name: CubeRaspberryLib3
Version: 0.1.15
Summary: CubeRaspberryLib driver adapted to Python3 version
Home-page: https://github.com/rikonaka/CubeRaspberryLib3
Author: RikoNaka
Author-email: xxy1836@gmail.com
Keywords: raspberry,pi,driver
Classifier: Programming Language :: Python :: 3
Classifier: Operating System :: OS Independent
Requires-Python: >=3.6
License-File: LICENSE
Requires-Dist: smbus2>=0.5.0
Requires-Dist: pillow>=11.3.0
Requires-Dist: Adafruit_SSD1306>=1.6.2
Dynamic: license-file
